show_recursion_tree/__init__.py
show_recursion_tree/show_recursion_tree_main.py
show_recursion_tree/helpers/classes.py
show_recursion_tree/helpers/main_helper.py
show_recursion_tree-0.0.5.dist-info/METADATA
show_recursion_tree-0.0.5.dist-info/WHEEL
show_recursion_tree-0.0.5.dist-info/licenses/LICENSE
show_recursion_tree-0.0.5.dist-info/RECORD
