Metadata-Version: 2.4
Name: show_recursion_tree
Version: 0.0.5
Summary: print recursion trees in terminal
Project-URL: Homepage, https://github.com/zlliu246/show_recursion_tree
Project-URL: Issues, https://github.com/zlliu246/show_recursion_tree/issues
Author-email: Liu Zuo Lin <zlliu246@gmail.com>
License-File: LICENSE
Classifier: License :: OSI Approved :: MIT License
Classifier: Operating System :: OS Independent
Classifier: Programming Language :: Python :: 3
Requires-Python: >=3.8
Requires-Dist: colorama
Requires-Dist: pprint-tree
